Works/bound_flasher.v
// Module      : bound_flasher
// Author      : Thanh
// Date        : 2026/03/25
// Version     : v0r0
// Description : RTL Exercise 1 - Bound Flasher with 16 lamps (cumulative bar display)
//               All lamps from lamp[0] up to the current level are ON simultaneously.
//               "ON gradually from A to B" = level rises, adding one lamp per clock.
//               "OFF gradually from A to B" = level falls, removing one lamp per clock.

module bound_flasher (
  input  wire        clk,
  input  wire        rst_n,
  input  wire        flick,
  output reg  [15:0] lamp
);

  // State encoding parameters
  parameter IDLE     = 4'd0;   // All lamps OFF, wait for flick=1
  parameter ON_0_5   = 4'd1;   // ON: level 1->6  (lamp[0] to lamp[5], first state, no kickback)
  parameter OFF_5_0  = 4'd2;   // OFF: level 5->0 (lamp[5] down to all OFF)
  parameter ON_0_10  = 4'd3;   // ON: level 1->11 (lamp[0] to lamp[10], kickback check at level=6)
  parameter KB1_OFF  = 4'd4;   // Kickback1 OFF: level 5->0 (lamp[5] back to all OFF)
  parameter KB1_ON   = 4'd5;   // Kickback1 resume ON: level 1->11 (lamp[0] to lamp[10])
  parameter OFF_10_5 = 4'd6;   // OFF: level 10->6 (lamp[10] down to lamp[5] remaining)
  parameter ON_5_15  = 4'd7;   // ON: level 7->16 (lamp[6] to lamp[15], kickback check at level=11)
  parameter KB2_OFF  = 4'd8;   // Kickback2 OFF: level 10->6 (lamp[10] back to lamp[5] remaining)
  parameter KB2_ON   = 4'd9;   // Kickback2 resume ON: level 7->16 (lamp[6] to lamp[15])
  parameter OFF_15_0 = 4'd10;  // OFF: level 15->0 (lamp[15] down to all OFF, return to IDLE)

  // Level constants
  // level = number of lamps currently ON (lamp[0] through lamp[level-1] are ON)
  parameter LVL_0    = 5'd0;   // all lamps OFF
  parameter LVL_5    = 5'd6;   // lamp[0] to lamp[5] ON  (6 lamps)
  parameter LVL_10   = 5'd11;  // lamp[0] to lamp[10] ON (11 lamps)
  parameter LVL_15   = 5'd16;  // lamp[0] to lamp[15] ON (16 lamps = all ON)

  // FF registers (state and lamp level)
  reg [3:0] state;
  reg [4:0] level;

  // Non-FF registers (combinational next values)
  reg [3:0] next_state;
  reg [4:0] next_level;

  // Sequential: update state and level on clock edge
  always @(posedge clk or negedge rst_n) begin
    if (!rst_n) begin
      state <= IDLE;
      level <= LVL_0;
    end else begin
      state <= next_state;
      level <= next_level;
    end
  end

  // Combinational: next-state and next-level logic
  always @(state or level or flick) begin
    next_state = state;
    next_level = level;

    case (state)
      IDLE: begin
        next_level = LVL_0;
        if (flick) begin
          next_state = ON_0_5;
          next_level = 5'd1;   // lamp[0] turns ON immediately
        end
      end

      // Step 1: ON lamp[0] to lamp[5], no kickback (first state)
      // level rises from 1 to 6; at level=6 (lamp[5] reached), transition to OFF
      ON_0_5: begin
        if (level == LVL_5) begin
          next_state = OFF_5_0;
          next_level = LVL_5 - 5'd1;  // lamp[5] starts turning OFF
        end else begin
          next_level = level + 5'd1;
        end
      end

      // Step 2: OFF lamp[5] to lamp[0], then all OFF
      // level falls from 5 to 0; at level=0 (all OFF), transition to ON
      OFF_5_0: begin
        if (level == LVL_0) begin
          next_state = ON_0_10;
          next_level = 5'd1;   // lamp[0] turns ON immediately
        end else begin
          next_level = level - 5'd1;
        end
      end

      // Step 3: ON lamp[0] to lamp[10], kickback check when lamp[5] is the top (level=6)
      ON_0_10: begin
        if (level == LVL_10) begin
          next_state = OFF_10_5;
          next_level = LVL_10 - 5'd1; // lamp[10] starts turning OFF
        end else if ((level == LVL_5) && flick) begin
          next_state = KB1_OFF;
          next_level = LVL_5 - 5'd1;  // kickback: lamp[5] starts turning OFF
        end else begin
          next_level = level + 5'd1;
        end
      end

      // Kickback1: OFF from lamp[5] all the way to lamp[0] (all OFF)
      KB1_OFF: begin
        if (level == LVL_0) begin
          next_state = KB1_ON;
          next_level = 5'd1;
        end else begin
          next_level = level - 5'd1;
        end
      end

      // Kickback1 resume: ON lamp[0] to lamp[10], no second kickback
      KB1_ON: begin
        if (level == LVL_10) begin
          next_state = OFF_10_5;
          next_level = LVL_10 - 5'd1;
        end else begin
          next_level = level + 5'd1;
        end
      end

      // Step 4: OFF lamp[10] down to lamp[5] (lamp[0] to lamp[5] remain ON)
      OFF_10_5: begin
        if (level == LVL_5) begin
          next_state = ON_5_15;
          next_level = LVL_5 + 5'd1;  // lamp[6] starts turning ON
        end else begin
          next_level = level - 5'd1;
        end
      end

      // Step 5: ON lamp[6] to lamp[15], kickback check when lamp[10] is the top (level=11)
      ON_5_15: begin
        if (level == LVL_15) begin
          next_state = OFF_15_0;
          next_level = LVL_15 - 5'd1; // lamp[15] starts turning OFF
        end else if ((level == LVL_10) && flick) begin
          next_state = KB2_OFF;
          next_level = LVL_10 - 5'd1; // kickback: lamp[10] starts turning OFF
        end else begin
          next_level = level + 5'd1;
        end
      end

      // Kickback2: OFF from lamp[10] down to lamp[5] (lamp[0] to lamp[5] remain ON)
      KB2_OFF: begin
        if (level == LVL_5) begin
          next_state = KB2_ON;
          next_level = LVL_5 + 5'd1;  // lamp[6] starts turning ON again
        end else begin
          next_level = level - 5'd1;
        end
      end

      // Kickback2 resume: ON lamp[6] to lamp[15], no second kickback
      KB2_ON: begin
        if (level == LVL_15) begin
          next_state = OFF_15_0;
          next_level = LVL_15 - 5'd1;
        end else begin
          next_level = level + 5'd1;
        end
      end

      // Step 6: OFF lamp[15] down to lamp[0], then all OFF, return to IDLE
      OFF_15_0: begin
        if (level == LVL_0) begin
          next_state = IDLE;
          next_level = LVL_0;
        end else begin
          next_level = level - 5'd1;
        end
      end

      // Non-reachable states: safe return to IDLE
      default: begin
        next_state = IDLE;
        next_level = LVL_0;
      end
    endcase
  end

  // Combinational: output logic (Moore)
  // lamp[i] = 1 if i < level, else 0  -->  lamp = (1 << level) - 1
  // Special case: level=16 uses 16'hFFFF (all ON) to avoid 16-bit overflow
  always @(state or level) begin
    if (state == IDLE) begin
      lamp = 16'd0;
    end else begin
      // (16'd1 << level) - 16'd1 works for level 0-16:
      // level=0  -> 0          level=6  -> 16'h003F  level=11 -> 16'h07FF
      // level=16 -> 16'hFFFF   (1<<16 overflows 16-bit to 0, 0-1 wraps to 16'hFFFF)
      lamp = (16'd1 << level) - 16'd1;
    end
  end

endmodule

Works/bound_flasher_tb.v
// Module      : bound_flasher_tb
// Author      : Thanh
// Date        : 2026/03/25
// Version     : v0r0
// Description : Testbench for bound_flasher
//               Verifies cumulative bar-graph lamp behavior.

`timescale 1ns/1ps

module bound_flasher_tb;

  // DUT ports
  reg        clk;
  reg        rst_n;
  reg        flick;
  wire [15:0] lamp;

  // DUT instance
  bound_flasher bound_flasher_01 (
    .clk   (clk),
    .rst_n (rst_n),
    .flick (flick),
    .lamp  (lamp)
  );

  // 10 ns clock (100 MHz)
  always #5 clk = ~clk;

  // Helper: count how many lamps are ON (should always be contiguous from L0)
  function [4:0] count_lamps;
    input [15:0] lmp;
    integer i;
    begin
      count_lamps = 0;
      for (i = 0; i < 16; i = i + 1) begin
        if (lmp[i]) begin
          count_lamps = count_lamps + 1;
        end
      end
    end
  endfunction

  // Helper: assert reset to put machine back into a clean IDLE state
  task do_reset;
    begin
      rst_n = 0;
      flick = 0;
      @(posedge clk); #1;
      @(posedge clk); #1;
      rst_n = 1;
      @(posedge clk); #1;
    end
  endtask

  integer cyc;

  initial begin
    clk   = 0;
    rst_n = 0;
    flick = 0;
    do_reset;

    // ------------------------------------------------------------------
    // TEST 1: Normal full sequence, no kickback (flick=0 after start)
    // Expected level peaks: 6, 11, 16
    // Expected level valleys: 0, 6, 0  ->  returns to IDLE
    // ------------------------------------------------------------------
    $display("=== TEST 1: Normal sequence (no kickback) ===");
    flick = 1;
    @(posedge clk); #1;  // machine enters ON_0_5
    flick = 0;           // drop flick: no kickback will fire

    for (cyc = 0; cyc < 60; cyc = cyc + 1) begin
      $display("  cyc=%0d  level=%0d  lamp=%b", cyc, count_lamps(lamp), lamp);
      @(posedge clk); #1;
    end

    if (lamp === 16'd0) begin
      $display("  PASS: Machine returned to IDLE (lamp=0)");
    end else begin
      $display("  FAIL: Expected IDLE, got %b (level=%0d)", lamp, count_lamps(lamp));
    end
    $display("--- Test 1 done ---");

    // ------------------------------------------------------------------
    // TEST 2: Kickback at both lamp[5] and lamp[10] (flick=1 throughout)
    // Full kickback sequence takes ~75 clocks.
    // Drop flick at cycle 60 to prevent re-start when machine returns to IDLE.
    // ------------------------------------------------------------------
    $display("=== TEST 2: Both kickbacks (flick=1, drop before IDLE) ===");
    do_reset;
    flick = 1;
    @(posedge clk); #1;  // machine enters ON_0_5

    for (cyc = 0; cyc < 60; cyc = cyc + 1) begin
      $display("  cyc=%0d  level=%0d  lamp=%b", cyc, count_lamps(lamp), lamp);
      @(posedge clk); #1;
    end
    // Drop flick now (before machine reaches IDLE ~cycle 75) so it won't restart
    flick = 0;

    for (cyc = 60; cyc < 90; cyc = cyc + 1) begin
      $display("  cyc=%0d  level=%0d  lamp=%b", cyc, count_lamps(lamp), lamp);
      @(posedge clk); #1;
    end

    if (lamp === 16'd0) begin
      $display("  PASS: Machine returned to IDLE after kickback sequence");
    end else begin
      $display("  FAIL: Expected IDLE, got level=%0d", count_lamps(lamp));
    end
    $display("--- Test 2 done ---");

    // ------------------------------------------------------------------
    // TEST 3: IDLE with flick=0 - all lamps must stay OFF
    // ------------------------------------------------------------------
    $display("=== TEST 3: IDLE with flick=0, lamps must be OFF ===");
    do_reset;
    flick = 0;
    repeat (5) begin
      @(posedge clk); #1;
      if (lamp !== 16'd0) begin
        $display("  FAIL: lamp should be 0 in IDLE, got %b", lamp);
      end
    end
    $display("  PASS: All lamps OFF in IDLE with flick=0");
    $display("--- Test 3 done ---");

    // ------------------------------------------------------------------
    // TEST 4: Verify step 1 peak = 16'h003F (lamp[0:5] ON, level=6)
    // After 6 clocks from start, level should reach 6.
    // ------------------------------------------------------------------
    $display("=== TEST 4: Step 1 peak = 16'h003F (lamp[0:5] all ON) ===");
    do_reset;
    // Clock 1: flick=1 -> enter ON_0_5, level=1
    flick = 1;
    @(posedge clk); #1;
    flick = 0;
    $display("  clock 1: level=%0d (expect 1)", count_lamps(lamp));
    // Clocks 2-5: level rises 2,3,4,5
    repeat (4) begin
      @(posedge clk); #1;
    end
    $display("  clock 5: level=%0d (expect 5)", count_lamps(lamp));
    // Clock 6: level should reach 6
    @(posedge clk); #1;
    $display("  clock 6: level=%0d  lamp=16'h%04h (expect 16'h003F)", count_lamps(lamp), lamp);
    if (lamp === 16'h003F) begin
      $display("  PASS: Step 1 peak = 16'h003F");
    end else begin
      $display("  FAIL: Expected 16'h003F, got 16'h%04h", lamp);
    end
    // Let machine complete so no loose ends
    flick = 0;
    repeat (60) @(posedge clk);
    $display("--- Test 4 done ---");

    // ------------------------------------------------------------------
    // TEST 5: Verify step 4 valley = 16'h003F (lamp[0:5] stay ON, level=6)
    // After step 4 (OFF 10->5), lamp[0:5] must remain ON.
    // ------------------------------------------------------------------
    $display("=== TEST 5: Step 4 valley = 16'h003F (lamp[0:5] remain ON) ===");
    do_reset;
    flick = 1;
    @(posedge clk); #1;
    flick = 0;
    // Wait until OFF_10_5 ends (step 4 ends):
    // From Test 1 output: step 4 valley (level=6) appears at cyc=27
    // = 27 additional clocks after the initial start clock
    repeat (26) @(posedge clk);
    @(posedge clk); #1;
    $display("  step4 valley: level=%0d  lamp=16'h%04h (expect 16'h003F)", count_lamps(lamp), lamp);
    if (lamp === 16'h003F) begin
      $display("  PASS: Step 4 valley = 16'h003F (lamp[0:5] remain ON)");
    end else begin
      $display("  FAIL: Expected 16'h003F, got 16'h%04h", lamp);
    end
    repeat (40) @(posedge clk);
    $display("--- Test 5 done ---");

    $display("=== Simulation complete ===");
    $finish;
  end

  // Dump waveforms for GTKWave
  initial begin
    $dumpfile("bound_flasher.vcd");
    $dumpvars(0, bound_flasher_tb);
  end

endmodule

Works/bound_flasher.vcd
$date
	Wed Mar 25 03:57:05 2026
$end
$version
	Icarus Verilog
$end
$timescale
	1ps
$end
$scope module bound_flasher_tb $end
$var wire 16 ! lamp [15:0] $end
$var reg 1 " clk $end
$var reg 1 # flick $end
$var reg 1 $ rst_n $end
$var integer 32 % cyc [31:0] $end
$scope function count_lamps $end
$var reg 16 & lmp [15:0] $end
$var integer 32 ' i [31:0] $end
$upscope $end
$scope module bound_flasher_01 $end
$var wire 1 " clk $end
$var wire 1 # flick $end
$var wire 1 $ rst_n $end
$var parameter 4 ( IDLE $end
$var parameter 4 ) KB1_OFF $end
$var parameter 4 * KB1_ON $end
$var parameter 4 + KB2_OFF $end
$var parameter 4 , KB2_ON $end
$var parameter 5 - LVL_0 $end
$var parameter 5 . LVL_10 $end
$var parameter 5 / LVL_15 $end
$var parameter 5 0 LVL_5 $end
$var parameter 4 1 OFF_10_5 $end
$var parameter 4 2 OFF_15_0 $end
$var parameter 4 3 OFF_5_0 $end
$var parameter 4 4 ON_0_10 $end
$var parameter 4 5 ON_0_5 $end
$var parameter 4 6 ON_5_15 $end
$var reg 16 7 lamp [15:0] $end
$var reg 5 8 level [4:0] $end
$var reg 5 9 next_level [4:0] $end
$var reg 4 : next_state [3:0] $end
$var reg 4 ; state [3:0] $end
$upscope $end
$scope task do_reset $end
$upscope $end
$upscope $end
$enddefinitions $end
$comment Show the parameter values. $end
$dumpall
b111 6
b1 5
b11 4
b10 3
b1010 2
b110 1
b110 0
b10000 /
b1011 .
b0 -
b1001 ,
b1000 +
b101 *
b100 )
b0 (
$end
#0
$dumpvars
b0 ;
b0 :
b0 9
b0 8
b0 7
bx '
bx &
bx %
0$
0#
0"
b0 !
$end
#5000
1"
#10000
0"
#15000
1"
#16000
1$
#20000
0"
#25000
1"
#26000
b1 9
b1 :
1#
#30000
0"
#35000
b1 !
b1 7
b10 9
b1 8
b1 ;
1"
#36000
b10 9
b10000 '
b1 &
b0 %
0#
#40000
0"
#45000
b11 !
b11 7
b11 9
b10 8
1"
#46000
b10000 '
b11 &
b1 %
#50000
0"
#55000
b111 !
b111 7
b100 9
b11 8
1"
#56000
b10000 '
b111 &
b10 %
#60000
0"
#65000
b1111 !
b1111 7
b101 9
b100 8
1"
#66000
b10000 '
b1111 &
b11 %
#70000
0"
#75000
b11111 !
b11111 7
b110 9
b101 8
1"
#76000
b10000 '
b11111 &
b100 %
#80000
0"
#85000
b111111 !
b111111 7
b101 9
b10 :
b110 8
1"
#86000
b10000 '
b111111 &
b101 %
#90000
0"
#95000
b11111 !
b11111 7
b100 9
b101 8
b10 ;
1"
#96000
b10000 '
b11111 &
b110 %
#100000
0"
#105000
b1111 !
b1111 7
b11 9
b100 8
1"
#106000
b10000 '
b1111 &
b111 %
#110000
0"
#115000
b111 !
b111 7
b10 9
b11 8
1"
#116000
b10000 '
b111 &
b1000 %
#120000
0"
#125000
b11 !
b11 7
b1 9
b10 8
1"
#126000
b10000 '
b11 &
b1001 %
#130000
0"
#135000
b1 !
b1 7
b0 9
b1 8
1"
#136000
b10000 '
b1 &
b1010 %
#140000
0"
#145000
b0 !
b0 7
b1 9
b11 :
b0 8
1"
#146000
b10000 '
b0 &
b1011 %
#150000
0"
#155000
b1 !
b1 7
b10 9
b1 8
b11 ;
1"
#156000
b10000 '
b1 &
b1100 %
#160000
0"
#165000
b11 !
b11 7
b11 9
b10 8
1"
#166000
b10000 '
b11 &
b1101 %
#170000
0"
#175000
b111 !
b111 7
b100 9
b11 8
1"
#176000
b10000 '
b111 &
b1110 %
#180000
0"
#185000
b1111 !
b1111 7
b101 9
b100 8
1"
#186000
b10000 '
b1111 &
b1111 %
#190000
0"
#195000
b11111 !
b11111 7
b110 9
b101 8
1"
#196000
b10000 '
b11111 &
b10000 %
#200000
0"
#205000
b111111 !
b111111 7
b111 9
b110 8
1"
#206000
b10000 '
b111111 &
b10001 %
#210000
0"
#215000
b1111111 !
b1111111 7
b1000 9
b111 8
1"
#216000
b10000 '
b1111111 &
b10010 %
#220000
0"
#225000
b11111111 !
b11111111 7
b1001 9
b1000 8
1"
#226000
b10000 '
b11111111 &
b10011 %
#230000
0"
#235000
b111111111 !
b111111111 7
b1010 9
b1001 8
1"
#236000
b10000 '
b111111111 &
b10100 %
#240000
0"
#245000
b1111111111 !
b1111111111 7
b1011 9
b1010 8
1"
#246000
b10000 '
b1111111111 &
b10101 %
#250000
0"
#255000
b11111111111 !
b11111111111 7
b1010 9
b110 :
b1011 8
1"
#256000
b10000 '
b11111111111 &
b10110 %
#260000
0"
#265000
b1111111111 !
b1111111111 7
b1001 9
b1010 8
b110 ;
1"
#266000
b10000 '
b1111111111 &
b10111 %
#270000
0"
#275000
b111111111 !
b111111111 7
b1000 9
b1001 8
1"
#276000
b10000 '
b111111111 &
b11000 %
#280000
0"
#285000
b11111111 !
b11111111 7
b111 9
b1000 8
1"
#286000
b10000 '
b11111111 &
b11001 %
#290000
0"
#295000
b1111111 !
b1111111 7
b110 9
b111 8
1"
#296000
b10000 '
b1111111 &
b11010 %
#300000
0"
#305000
b111111 !
b111111 7
b111 9
b111 :
b110 8
1"
#306000
b10000 '
b111111 &
b11011 %
#310000
0"
#315000
b1111111 !
b1111111 7
b1000 9
b111 8
b111 ;
1"
#316000
b10000 '
b1111111 &
b11100 %
#320000
0"
#325000
b11111111 !
b11111111 7
b1001 9
b1000 8
1"
#326000
b10000 '
b11111111 &
b11101 %
#330000
0"
#335000
b111111111 !
b111111111 7
b1010 9
b1001 8
1"
#336000
b10000 '
b111111111 &
b11110 %
#340000
0"
#345000
b1111111111 !
b1111111111 7
b1011 9
b1010 8
1"
#346000
b10000 '
b1111111111 &
b11111 %
#350000
0"
#355000
b11111111111 !
b11111111111 7
b1100 9
b1011 8
1"
#356000
b10000 '
b11111111111 &
b100000 %
#360000
0"
#365000
b111111111111 !
b111111111111 7
b1101 9
b1100 8
1"
#366000
b10000 '
b111111111111 &
b100001 %
#370000
0"
#375000
b1111111111111 !
b1111111111111 7
b1110 9
b1101 8
1"
#376000
b10000 '
b1111111111111 &
b100010 %
#380000
0"
#385000
b11111111111111 !
b11111111111111 7
b1111 9
b1110 8
1"
#386000
b10000 '
b11111111111111 &
b100011 %
#390000
0"
#395000
b111111111111111 !
b111111111111111 7
b10000 9
b1111 8
1"
#396000
b10000 '
b111111111111111 &
b100100 %
#400000
0"
#405000
b1111111111111111 !
b1111111111111111 7
b1111 9
b1010 :
b10000 8
1"
#406000
b10000 '
b1111111111111111 &
b100101 %
#410000
0"
#415000
b111111111111111 !
b111111111111111 7
b1110 9
b1111 8
b1010 ;
1"
#416000
b10000 '
b111111111111111 &
b100110 %
#420000
0"
#425000
b11111111111111 !
b11111111111111 7
b1101 9
b1110 8
1"
#426000
b10000 '
b11111111111111 &
b100111 %
#430000
0"
#435000
b1111111111111 !
b1111111111111 7
b1100 9
b1101 8
1"
#436000
b10000 '
b1111111111111 &
b101000 %
#440000
0"
#445000
b111111111111 !
b111111111111 7
b1011 9
b1100 8
1"
#446000
b10000 '
b111111111111 &
b101001 %
#450000
0"
#455000
b11111111111 !
b11111111111 7
b1010 9
b1011 8
1"
#456000
b10000 '
b11111111111 &
b101010 %
#460000
0"
#465000
b1111111111 !
b1111111111 7
b1001 9
b1010 8
1"
#466000
b10000 '
b1111111111 &
b101011 %
#470000
0"
#475000
b111111111 !
b111111111 7
b1000 9
b1001 8
1"
#476000
b10000 '
b111111111 &
b101100 %
#480000
0"
#485000
b11111111 !
b11111111 7
b111 9
b1000 8
1"
#486000
b10000 '
b11111111 &
b101101 %
#490000
0"
#495000
b1111111 !
b1111111 7
b110 9
b111 8
1"
#496000
b10000 '
b1111111 &
b101110 %
#500000
0"
#505000
b111111 !
b111111 7
b101 9
b110 8
1"
#506000
b10000 '
b111111 &
b101111 %
#510000
0"
#515000
b11111 !
b11111 7
b100 9
b101 8
1"
#516000
b10000 '
b11111 &
b110000 %
#520000
0"
#525000
b1111 !
b1111 7
b11 9
b100 8
1"
#526000
b10000 '
b1111 &
b110001 %
#530000
0"
#535000
b111 !
b111 7
b10 9
b11 8
1"
#536000
b10000 '
b111 &
b110010 %
#540000
0"
#545000
b11 !
b11 7
b1 9
b10 8
1"
#546000
b10000 '
b11 &
b110011 %
#550000
0"
#555000
b1 !
b1 7
b0 9
b1 8
1"
#556000
b10000 '
b1 &
b110100 %
#560000
0"
#565000
b0 !
b0 7
b0 :
b0 8
1"
#566000
b10000 '
b0 &
b110101 %
#570000
0"
#575000
b0 ;
1"
#576000
b10000 '
b110110 %
#580000
0"
#585000
1"
#586000
b10000 '
b110111 %
#590000
0"
#595000
1"
#596000
b10000 '
b111000 %
#600000
0"
#605000
1"
#606000
b10000 '
b111001 %
#610000
0"
#615000
1"
#616000
b10000 '
b111010 %
#620000
0"
#625000
1"
#626000
b10000 '
b111011 %
#630000
0"
#635000
1"
#636000
0$
b111100 %
#640000
0"
#645000
1"
#650000
0"
#655000
1"
#656000
1$
#660000
0"
#665000
1"
#666000
b1 9
b1 :
1#
#670000
0"
#675000
b1 !
b1 7
b10 9
b1 8
b1 ;
1"
#676000
b10000 '
b1 &
b0 %
#680000
0"
#685000
b11 !
b11 7
b11 9
b10 8
1"
#686000
b10000 '
b11 &
b1 %
#690000
0"
#695000
b111 !
b111 7
b100 9
b11 8
1"
#696000
b10000 '
b111 &
b10 %
#700000
0"
#705000
b1111 !
b1111 7
b101 9
b100 8
1"
#706000
b10000 '
b1111 &
b11 %
#710000
0"
#715000
b11111 !
b11111 7
b110 9
b101 8
1"
#716000
b10000 '
b11111 &
b100 %
#720000
0"
#725000
b111111 !
b111111 7
b101 9
b10 :
b110 8
1"
#726000
b10000 '
b111111 &
b101 %
#730000
0"
#735000
b11111 !
b11111 7
b100 9
b101 8
b10 ;
1"
#736000
b10000 '
b11111 &
b110 %
#740000
0"
#745000
b1111 !
b1111 7
b11 9
b100 8
1"
#746000
b10000 '
b1111 &
b111 %
#750000
0"
#755000
b111 !
b111 7
b10 9
b11 8
1"
#756000
b10000 '
b111 &
b1000 %
#760000
0"
#765000
b11 !
b11 7
b1 9
b10 8
1"
#766000
b10000 '
b11 &
b1001 %
#770000
0"
#775000
b1 !
b1 7
b0 9
b1 8
1"
#776000
b10000 '
b1 &
b1010 %
#780000
0"
#785000
b0 !
b0 7
b1 9
b11 :
b0 8
1"
#786000
b10000 '
b0 &
b1011 %
#790000
0"
#795000
b1 !
b1 7
b10 9
b1 8
b11 ;
1"
#796000
b10000 '
b1 &
b1100 %
#800000
0"
#805000
b11 !
b11 7
b11 9
b10 8
1"
#806000
b10000 '
b11 &
b1101 %
#810000
0"
#815000
b111 !
b111 7
b100 9
b11 8
1"
#816000
b10000 '
b111 &
b1110 %
#820000
0"
#825000
b1111 !
b1111 7
b101 9
b100 8
1"
#826000
b10000 '
b1111 &
b1111 %
#830000
0"
#835000
b11111 !
b11111 7
b110 9
b101 8
1"
#836000
b10000 '
b11111 &
b10000 %
#840000
0"
#845000
b111111 !
b111111 7
b101 9
b100 :
b110 8
1"
#846000
b10000 '
b111111 &
b10001 %
#850000
0"
#855000
b11111 !
b11111 7
b100 9
b101 8
b100 ;
1"
#856000
b10000 '
b11111 &
b10010 %
#860000
0"
#865000
b1111 !
b1111 7
b11 9
b100 8
1"
#866000
b10000 '
b1111 &
b10011 %
#870000
0"
#875000
b111 !
b111 7
b10 9
b11 8
1"
#876000
b10000 '
b111 &
b10100 %
#880000
0"
#885000
b11 !
b11 7
b1 9
b10 8
1"
#886000
b10000 '
b11 &
b10101 %
#890000
0"
#895000
b1 !
b1 7
b0 9
b1 8
1"
#896000
b10000 '
b1 &
b10110 %
#900000
0"
#905000
b0 !
b0 7
b1 9
b101 :
b0 8
1"
#906000
b10000 '
b0 &
b10111 %
#910000
0"
#915000
b1 !
b1 7
b10 9
b1 8
b101 ;
1"
#916000
b10000 '
b1 &
b11000 %
#920000
0"
#925000
b11 !
b11 7
b11 9
b10 8
1"
#926000
b10000 '
b11 &
b11001 %
#930000
0"
#935000
b111 !
b111 7
b100 9
b11 8
1"
#936000
b10000 '
b111 &
b11010 %
#940000
0"
#945000
b1111 !
b1111 7
b101 9
b100 8
1"
#946000
b10000 '
b1111 &
b11011 %
#950000
0"
#955000
b11111 !
b11111 7
b110 9
b101 8
1"
#956000
b10000 '
b11111 &
b11100 %
#960000
0"
#965000
b111111 !
b111111 7
b111 9
b110 8
1"
#966000
b10000 '
b111111 &
b11101 %
#970000
0"
#975000
b1111111 !
b1111111 7
b1000 9
b111 8
1"
#976000
b10000 '
b1111111 &
b11110 %
#980000
0"
#985000
b11111111 !
b11111111 7
b1001 9
b1000 8
1"
#986000
b10000 '
b11111111 &
b11111 %
#990000
0"
#995000
b111111111 !
b111111111 7
b1010 9
b1001 8
1"
#996000
b10000 '
b111111111 &
b100000 %
#1000000
0"
#1005000
b1111111111 !
b1111111111 7
b1011 9
b1010 8
1"
#1006000
b10000 '
b1111111111 &
b100001 %
#1010000
0"
#1015000
b11111111111 !
b11111111111 7
b1010 9
b110 :
b1011 8
1"
#1016000
b10000 '
b11111111111 &
b100010 %
#1020000
0"
#1025000
b1111111111 !
b1111111111 7
b1001 9
b1010 8
b110 ;
1"
#1026000
b10000 '
b1111111111 &
b100011 %
#1030000
0"
#1035000
b111111111 !
b111111111 7
b1000 9
b1001 8
1"
#1036000
b10000 '
b111111111 &
b100100 %
#1040000
0"
#1045000
b11111111 !
b11111111 7
b111 9
b1000 8
1"
#1046000
b10000 '
b11111111 &
b100101 %
#1050000
0"
#1055000
b1111111 !
b1111111 7
b110 9
b111 8
1"
#1056000
b10000 '
b1111111 &
b100110 %
#1060000
0"
#1065000
b111111 !
b111111 7
b111 9
b111 :
b110 8
1"
#1066000
b10000 '
b111111 &
b100111 %
#1070000
0"
#1075000
b1111111 !
b1111111 7
b1000 9
b111 8
b111 ;
1"
#1076000
b10000 '
b1111111 &
b101000 %
#1080000
0"
#1085000
b11111111 !
b11111111 7
b1001 9
b1000 8
1"
#1086000
b10000 '
b11111111 &
b101001 %
#1090000
0"
#1095000
b111111111 !
b111111111 7
b1010 9
b1001 8
1"
#1096000
b10000 '
b111111111 &
b101010 %
#1100000
0"
#1105000
b1111111111 !
b1111111111 7
b1011 9
b1010 8
1"
#1106000
b10000 '
b1111111111 &
b101011 %
#1110000
0"
#1115000
b11111111111 !
b11111111111 7
b1010 9
b1000 :
b1011 8
1"
#1116000
b10000 '
b11111111111 &
b101100 %
#1120000
0"
#1125000
b1111111111 !
b1111111111 7
b1001 9
b1010 8
b1000 ;
1"
#1126000
b10000 '
b1111111111 &
b101101 %
#1130000
0"
#1135000
b111111111 !
b111111111 7
b1000 9
b1001 8
1"
#1136000
b10000 '
b111111111 &
b101110 %
#1140000
0"
#1145000
b11111111 !
b11111111 7
b111 9
b1000 8
1"
#1146000
b10000 '
b11111111 &
b101111 %
#1150000
0"
#1155000
b1111111 !
b1111111 7
b110 9
b111 8
1"
#1156000
b10000 '
b1111111 &
b110000 %
#1160000
0"
#1165000
b111111 !
b111111 7
b111 9
b1001 :
b110 8
1"
#1166000
b10000 '
b111111 &
b110001 %
#1170000
0"
#1175000
b1111111 !
b1111111 7
b1000 9
b111 8
b1001 ;
1"
#1176000
b10000 '
b1111111 &
b110010 %
#1180000
0"
#1185000
b11111111 !
b11111111 7
b1001 9
b1000 8
1"
#1186000
b10000 '
b11111111 &
b110011 %
#1190000
0"
#1195000
b111111111 !
b111111111 7
b1010 9
b1001 8
1"
#1196000
b10000 '
b111111111 &
b110100 %
#1200000
0"
#1205000
b1111111111 !
b1111111111 7
b1011 9
b1010 8
1"
#1206000
b10000 '
b1111111111 &
b110101 %
#1210000
0"
#1215000
b11111111111 !
b11111111111 7
b1100 9
b1011 8
1"
#1216000
b10000 '
b11111111111 &
b110110 %
#1220000
0"
#1225000
b111111111111 !
b111111111111 7
b1101 9
b1100 8
1"
#1226000
b10000 '
b111111111111 &
b110111 %
#1230000
0"
#1235000
b1111111111111 !
b1111111111111 7
b1110 9
b1101 8
1"
#1236000
b10000 '
b1111111111111 &
b111000 %
#1240000
0"
#1245000
b11111111111111 !
b11111111111111 7
b1111 9
b1110 8
1"
#1246000
b10000 '
b11111111111111 &
b111001 %
#1250000
0"
#1255000
b111111111111111 !
b111111111111111 7
b10000 9
b1111 8
1"
#1256000
b10000 '
b111111111111111 &
b111010 %
#1260000
0"
#1265000
b1111111111111111 !
b1111111111111111 7
b1111 9
b1010 :
b10000 8
1"
#1266000
b10000 '
b1111111111111111 &
b111011 %
#1270000
0"
#1275000
b111111111111111 !
b111111111111111 7
b1110 9
b1111 8
b1010 ;
1"
#1276000
b1110 9
b10000 '
b111111111111111 &
0#
b111100 %
#1280000
0"
#1285000
b11111111111111 !
b11111111111111 7
b1101 9
b1110 8
1"
#1286000
b10000 '
b11111111111111 &
b111101 %
#1290000
0"
#1295000
b1111111111111 !
b1111111111111 7
b1100 9
b1101 8
1"
#1296000
b10000 '
b1111111111111 &
b111110 %
#1300000
0"
#1305000
b111111111111 !
b111111111111 7
b1011 9
b1100 8
1"
#1306000
b10000 '
b111111111111 &
b111111 %
#1310000
0"
#1315000
b11111111111 !
b11111111111 7
b1010 9
b1011 8
1"
#1316000
b10000 '
b11111111111 &
b1000000 %
#1320000
0"
#1325000
b1111111111 !
b1111111111 7
b1001 9
b1010 8
1"
#1326000
b10000 '
b1111111111 &
b1000001 %
#1330000
0"
#1335000
b111111111 !
b111111111 7
b1000 9
b1001 8
1"
#1336000
b10000 '
b111111111 &
b1000010 %
#1340000
0"
#1345000
b11111111 !
b11111111 7
b111 9
b1000 8
1"
#1346000
b10000 '
b11111111 &
b1000011 %
#1350000
0"
#1355000
b1111111 !
b1111111 7
b110 9
b111 8
1"
#1356000
b10000 '
b1111111 &
b1000100 %
#1360000
0"
